fw_gear_mask_exporter/ExportRois.py
fw_gear_mask_exporter/MeasurementExporter.py
fw_gear_mask_exporter/__init__.py
fw_gear_mask_exporter/objects/Conversion.py
fw_gear_mask_exporter/objects/Files.py
fw_gear_mask_exporter/objects/Labels.py
fw_gear_mask_exporter/parser.py
fw_gear_mask_exporter/roi_tools.py
fw_gear_mask_exporter/workers/Collectors.py
fw_gear_mask_exporter/workers/Converters.py
fw_gear_mask_exporter/workers/Creators.py
fw_gear_mask_exporter/workers/Preppers.py
fw_gear_mask_exporter/workers/__init__.py
fw_gear_mask_exporter/workers/utils.py
fw_gear_mask_exporter-1.2.3.dist-info/METADATA
fw_gear_mask_exporter-1.2.3.dist-info/WHEEL
fw_gear_mask_exporter-1.2.3.dist-info/RECORD
